{
    "name": "Quizzes",
    "tagline": "For the thrill and pursuit of knowledge",
    "description": [
        "Pravega '21, the annual undergraduate fest of IISc Bangalore, presents a set of exciting quizzes for you to rack your brains over. So mark your calendars, and be there!"
    ],
    "subevents": [

    ],
    "modules": [
        {
            "heading": "Eligibility and Rules",
            "content": "School and college students (with valid institute ID Card) are allowed to participate. Teams can have upto 3 members. Cross-institutional teams are allowed. <br> The registration fee is Rs. 50 per team per quiz. However, if the same team is participating in all three quizzes, they can register for all three for a total of Rs. 100. <br> Registration for each quiz closes 3 hours before the quiz starts. <br> Students who have completed class 12 this year, or have passed out of college this year, can also participate.",
            "links": [
                {
                    "text": "Download detailed rules and regulations",
                    "file": "quizzes_rules.pdf"
                }
            ]
        },
        {
            "heading": "Quiz lineup",
            "lists": [
                {
                    "points": [
                        "<b>MELAS Quiz:</b> - materials by Sabyasachi Basu, hosted by Nishit Pandya, on 21 August, 9:30 am",
                        "<b>Sci-Biz-Tech Quiz:</b> by Adit Vishnu, on 21 August, 3 pm",
                        "<b>General Quiz:</b> by Major Chandrakant Nair, on 22 August, 3 pm"
                    ]
                }
            ]
        },
        {
            "heading": "Registration links",
            "lists": [
                {
                    "points": [
                        "<b>General Quiz:</b> <a href='https://forms.gle/MSJnM7HypD2it1Q37'>https://forms.gle/MSJnM7HypD2it1Q37</a>",
                        "<b>MELAS Quiz:</b> Registration is now closed.",
                        "<b>Sci-Biz-Tech Quiz:</b> Registration is now closed.",
                        "<b>Combined registration for all three quizzes:</b> Registration is now closed."
                    ]
                }
            ]
        }
    ],
    "events": [
        {
            "name": "MELAS Quiz",
            "date": "9:30 AM on 21<sup>st</sup> August"
        },
        {
            "name": "Sci-Biz-Tech Quiz",
            "date": "3 PM on 21<sup>st</sup> August"
        },
        {
            "name": "General Quiz",
            "date": "3PM on 22<sup>nd</sup> August"
        }
    ],
    "coords": [
        "Jitendriya Praharaj",
        "Upamanyu Yaddanapudi"
    ],
    "email": "quiz.pravega@gmail.com"
}
